{
  "version": "5",
  "dialect": "mysql",
  "id": "cc759da3-4724-4f2d-be34-fc8864921ea9",
  "prevId": "30a1a825-c2f2-4be6-8d11-eab6049afce4",
  "tables": {
    "github_profile": {
      "name": "github_profile",
      "columns": {
        "id": {
          "name": "id",
          "type": "int",
          "primaryKey": false,
          "notNull": true,
          "autoincrement": false
        },
        "login": {
          "name": "login",
          "type": "varchar(255)",
          "primaryKey": false,
          "notNull": true,
          "autoincrement": false
        },
        "points": {
          "name": "points",
          "type": "double",
          "primaryKey": false,
          "notNull": true,
          "autoincrement": false,
          "default": 0
        },
        "avatarUrl": {
          "name": "avatarUrl",
          "type": "text",
          "primaryKey": false,
          "notNull": false,
          "autoincrement": false
        }
      },
      "indexes": {
        "login_idx": {
          "name": "login_idx",
          "columns": ["(lower(`login`))"],
          "isUnique": true
        }
      },
      "foreignKeys": {},
      "compositePrimaryKeys": {
        "github_profile_id": {
          "name": "github_profile_id",
          "columns": ["id"]
        }
      },
      "uniqueConstraints": {},
      "checkConstraint": {}
    },
    "session": {
      "name": "session",
      "columns": {
        "createdAt": {
          "name": "createdAt",
          "type": "timestamp",
          "primaryKey": false,
          "notNull": true,
          "autoincrement": false,
          "default": "(now())"
        },
        "userAgent": {
          "name": "userAgent",
          "type": "text",
          "primaryKey": false,
          "notNull": false,
          "autoincrement": false
        },
        "userId": {
          "name": "userId",
          "type": "varchar(255)",
          "primaryKey": false,
          "notNull": true,
          "autoincrement": false
        },
        "token": {
          "name": "token",
          "type": "varchar(255)",
          "primaryKey": false,
          "notNull": true,
          "autoincrement": false
        }
      },
      "indexes": {},
      "foreignKeys": {
        "session_userId_user_id_fk": {
          "name": "session_userId_user_id_fk",
          "tableFrom": "session",
          "tableTo": "user",
          "columnsFrom": ["userId"],
          "columnsTo": ["id"],
          "onDelete": "cascade",
          "onUpdate": "no action"
        }
      },
      "compositePrimaryKeys": {
        "session_token": {
          "name": "session_token",
          "columns": ["token"]
        }
      },
      "uniqueConstraints": {},
      "checkConstraint": {}
    },
    "user": {
      "name": "user",
      "columns": {
        "id": {
          "name": "id",
          "type": "varchar(255)",
          "primaryKey": false,
          "notNull": true,
          "autoincrement": false
        },
        "email": {
          "name": "email",
          "type": "varchar(255)",
          "primaryKey": false,
          "notNull": true,
          "autoincrement": false
        },
        "type": {
          "name": "type",
          "type": "enum('user','organization')",
          "primaryKey": false,
          "notNull": true,
          "autoincrement": false
        },
        "name": {
          "name": "name",
          "type": "varchar(255)",
          "primaryKey": false,
          "notNull": true,
          "autoincrement": false
        },
        "image": {
          "name": "image",
          "type": "varchar(255)",
          "primaryKey": false,
          "notNull": false,
          "autoincrement": false
        },
        "createdAt": {
          "name": "createdAt",
          "type": "timestamp",
          "primaryKey": false,
          "notNull": true,
          "autoincrement": false,
          "default": "(now())"
        },
        "updatedAt": {
          "name": "updatedAt",
          "type": "timestamp",
          "primaryKey": false,
          "notNull": false,
          "autoincrement": false,
          "onUpdate": true
        },
        "githubId": {
          "name": "githubId",
          "type": "int",
          "primaryKey": false,
          "notNull": false,
          "autoincrement": false
        }
      },
      "indexes": {
        "email_idx": {
          "name": "email_idx",
          "columns": ["(lower(`email`))"],
          "isUnique": true
        }
      },
      "foreignKeys": {
        "user_githubId_github_profile_id_fk": {
          "name": "user_githubId_github_profile_id_fk",
          "tableFrom": "user",
          "tableTo": "github_profile",
          "columnsFrom": ["githubId"],
          "columnsTo": ["id"],
          "onDelete": "no action",
          "onUpdate": "no action"
        }
      },
      "compositePrimaryKeys": {
        "user_id": {
          "name": "user_id",
          "columns": ["id"]
        }
      },
      "uniqueConstraints": {},
      "checkConstraint": {}
    }
  },
  "views": {},
  "_meta": {
    "schemas": {},
    "tables": {},
    "columns": {
      "\"user\".\"created_at\"": "\"user\".\"createdAt\"",
      "\"user\".\"updated_at\"": "\"user\".\"updatedAt\""
    }
  },
  "internal": {
    "tables": {},
    "indexes": {
      "login_idx": {
        "columns": {
          "(lower(`login`))": {
            "isExpression": true
          }
        }
      },
      "email_idx": {
        "columns": {
          "(lower(`email`))": {
            "isExpression": true
          }
        }
      }
    }
  }
}
